LinuxCYizhanshiXuexi/README.md
LinuxCYizhanshiXuexi/__init__.py
LinuxCYizhanshiXuexi/__main__.py
LinuxCYizhanshiXuexi/file.epub
LinuxCYizhanshiXuexi/index.html
LinuxCYizhanshiXuexi/css/__init__.py
LinuxCYizhanshiXuexi/css/annotations.css
LinuxCYizhanshiXuexi/css/main.css
LinuxCYizhanshiXuexi/css/normalize.css
LinuxCYizhanshiXuexi/css/popup.css
LinuxCYizhanshiXuexi/font/__init__.py
LinuxCYizhanshiXuexi/font/fontello.eot
LinuxCYizhanshiXuexi/font/fontello.svg
LinuxCYizhanshiXuexi/font/fontello.ttf
LinuxCYizhanshiXuexi/font/fontello.woff
LinuxCYizhanshiXuexi/img/__init__.py
LinuxCYizhanshiXuexi/img/annotator-glyph-sprite.png
LinuxCYizhanshiXuexi/img/annotator-icon-sprite.png
LinuxCYizhanshiXuexi/img/apple-touch-icon.png
LinuxCYizhanshiXuexi/img/cancelfullscreen.png
LinuxCYizhanshiXuexi/img/close.png
LinuxCYizhanshiXuexi/img/fullscreen.png
LinuxCYizhanshiXuexi/img/loader.gif
LinuxCYizhanshiXuexi/img/menu-icon.png
LinuxCYizhanshiXuexi/img/save.png
LinuxCYizhanshiXuexi/img/saved.png
LinuxCYizhanshiXuexi/img/settings-s.png
LinuxCYizhanshiXuexi/img/settings.png
LinuxCYizhanshiXuexi/img/star.png
LinuxCYizhanshiXuexi/js/__init__.py
LinuxCYizhanshiXuexi/js/epub.js
LinuxCYizhanshiXuexi/js/epub.min.js
LinuxCYizhanshiXuexi/js/epub.min.map
LinuxCYizhanshiXuexi/js/hooks.min.js
LinuxCYizhanshiXuexi/js/hooks.min.map
LinuxCYizhanshiXuexi/js/reader.js
LinuxCYizhanshiXuexi/js/reader.js.map
LinuxCYizhanshiXuexi/js/reader.min.js
LinuxCYizhanshiXuexi/js/reader.min.map
LinuxCYizhanshiXuexi/js/hooks/__init__.py
LinuxCYizhanshiXuexi/js/hooks/extensions/__init__.py
LinuxCYizhanshiXuexi/js/hooks/extensions/highlight.js
LinuxCYizhanshiXuexi/js/libs/__init__.py
LinuxCYizhanshiXuexi/js/libs/jquery.min.js
LinuxCYizhanshiXuexi/js/libs/localforage.min.js
LinuxCYizhanshiXuexi/js/libs/screenfull.js
LinuxCYizhanshiXuexi/js/libs/screenfull.min.js
LinuxCYizhanshiXuexi/js/libs/zip.min.js
LinuxCYizhanshiXuexi/js/plugins/__init__.py
LinuxCYizhanshiXuexi/js/plugins/hypothesis.js
linux_c_yizhanshi_xuexi-2024.3.1.0.dist-info/METADATA
linux_c_yizhanshi_xuexi-2024.3.1.0.dist-info/WHEEL
linux_c_yizhanshi_xuexi-2024.3.1.0.dist-info/entry_points.txt
linux_c_yizhanshi_xuexi-2024.3.1.0.dist-info/top_level.txt
linux_c_yizhanshi_xuexi-2024.3.1.0.dist-info/RECORD
